README.rst
setup.py
ungog/__init__.py
ungog/ungog.py
ungog.egg-info/PKG-INFO
ungog.egg-info/SOURCES.txt
ungog.egg-info/dependency_links.txt
ungog.egg-info/entry_points.txt
ungog.egg-info/top_level.txt