Metadata-Version: 1.1
Name: ungog
Version: 0.0.2
Summary: ungoogleify your css
Home-page: https://github.com/kalikaneko/ungog/
Author: kali kaneko
Author-email: kali@sindominio.net
License: UNKNOWN
Platform: UNKNOWN
Classifier: Environment :: Console
Classifier: Programming Language :: Python :: 3
